simplekiq/__init__.py
simplekiq/base.py
simplekiq/constants.py
simplekiq/event.py
simplekiq/worker.py
simplekiq-0.0.2.data/scripts/__init__.py
simplekiq-0.0.2.dist-info/LICENSE
simplekiq-0.0.2.dist-info/METADATA
simplekiq-0.0.2.dist-info/WHEEL
simplekiq-0.0.2.dist-info/top_level.txt
simplekiq-0.0.2.dist-info/RECORD
