Metadata-Version: 2.1
Name: simplekiq
Version: 0.0.2
Summary: Python SideKiq Client
Home-page: https://github.com/charsyam/simplekiq
Author: DaeMyung Kang
Author-email: charsyam@gmail.com
License: UNKNOWN
Platform: any
